{
"type": "FeatureCollection",
"name": "parques",
"crs": { "type": "name", "properties": { "name": "urn:ogc:def:crs:OGC:1.3:CRS84" } },
"features": [
{ "type": "Feature", "properties": { "Instituição": "Parque Nacional da Serra da Capivara", "Cidade/Região": "São Raimundo Nonato e região", "Latitude": -8.7166802194703656, "Longitude": -42.601922720921593 }, "geometry": { "type": "Point", "coordinates": [ -42.601922720921593, -8.716680219470366 ] } },
{ "type": "Feature", "properties": { "Instituição": "Parque Nacional da Serra das Confusões", "Cidade/Região": "Caracol e região", "Latitude": -8.9229934208238539, "Longitude": -43.49548340020344 }, "geometry": { "type": "Point", "coordinates": [ -43.49548340020344, -8.922993420823854 ] } },
{ "type": "Feature", "properties": { "Instituição": "Parque Nacional de Sete Cidades", "Cidade/Região": "Piracuruca / Brasileira", "Latitude": -4.1049020974144543, "Longitude": -41.698156767659363 }, "geometry": { "type": "Point", "coordinates": [ -41.698156767659363, -4.104902097414454 ] } },
{ "type": "Feature", "properties": { "Instituição": "Parque Nacional das Nascentes do Rio Parnaíba", "Cidade/Região": "Divisa PI/MA/BA/TO", "Latitude": -10.009133839874288, "Longitude": -46.011415600073889 }, "geometry": { "type": "Point", "coordinates": [ -46.011415600073889, -10.009133839874288 ] } },
{ "type": "Feature", "properties": { "Instituição": "Parque Estadual Zoobotânico de Teresina", "Cidade/Região": "Teresina", "Latitude": -5.0381235195317755, "Longitude": -42.776867125148549 }, "geometry": { "type": "Point", "coordinates": [ -42.776867125148549, -5.038123519531776 ] } },
{ "type": "Feature", "properties": { "Instituição": "Área de Proteção Ambiental (APA) Delta do Parnaíba", "Cidade/Região": "Litoral do Piauí", "Latitude": -2.8222062348163299, "Longitude": -41.840589276357292 }, "geometry": { "type": "Point", "coordinates": [ -41.840589276357292, -2.82220623481633 ] } },
{ "type": "Feature", "properties": { "Instituição": "Parque Ambiental Encontro dos Rios", "Cidade/Região": "Teresina", "Latitude": -5.0352617013839271, "Longitude": -42.839186127130937 }, "geometry": { "type": "Point", "coordinates": [ -42.839186127130937, -5.035261701383927 ] } },
{ "type": "Feature", "properties": { "Instituição": "Parque Municipal Floresta Fóssil", "Cidade/Região": "Teresina", "Latitude": -5.0875889001243335, "Longitude": -42.788742038347003 }, "geometry": { "type": "Point", "coordinates": [ -42.788742038347003, -5.087588900124334 ] } }
]
}
